{"@t":"2023-11-08T09:43:18.9701678Z","@mt":"Acquiring MainDom.","SourceContext":"Umbraco.Cms.Core.Runtime.MainDom","ProcessId":8944,"ProcessName":"iisexpress","ThreadId":1,"ApplicationId":"3f3ed72a8d0f46228ba494c1a1aeb400115a9d84","MachineName":"IPS-025","Log4NetLevel":"INFO "}
{"@t":"2023-11-08T09:43:18.9854407Z","@mt":"Acquired MainDom.","SourceContext":"Umbraco.Cms.Core.Runtime.MainDom","ProcessId":8944,"ProcessName":"iisexpress","ThreadId":1,"ApplicationId":"3f3ed72a8d0f46228ba494c1a1aeb400115a9d84","MachineName":"IPS-025","Log4NetLevel":"INFO "}
{"@t":"2023-11-08T09:43:19.4424921Z","@mt":"{StartMessage} [Timing {TimingId}]","StartMessage":"Starting unattended package migration for UmbracoForms","TimingId":"74d5146","SourceContext":"Umbraco.Cms.Core.Logging.ProfilingLogger","ProcessId":8944,"ProcessName":"iisexpress","ThreadId":1,"ApplicationId":"3f3ed72a8d0f46228ba494c1a1aeb400115a9d84","MachineName":"IPS-025","Log4NetLevel":"INFO "}
{"@t":"2023-11-08T09:43:19.4715686Z","@mt":"Starting '{MigrationName}'...","MigrationName":"UmbracoForms","SourceContext":"Umbraco.Cms.Infrastructure.Migrations.MigrationPlanExecutor","ProcessId":8944,"ProcessName":"iisexpress","ThreadId":1,"ApplicationId":"3f3ed72a8d0f46228ba494c1a1aeb400115a9d84","MachineName":"IPS-025","Log4NetLevel":"INFO "}
{"@t":"2023-11-08T09:43:19.4716029Z","@mt":"At {OrigState}","OrigState":"{forms-init-state}","SourceContext":"Umbraco.Cms.Infrastructure.Migrations.MigrationPlanExecutor","ProcessId":8944,"ProcessName":"iisexpress","ThreadId":1,"ApplicationId":"3f3ed72a8d0f46228ba494c1a1aeb400115a9d84","MachineName":"IPS-025","Log4NetLevel":"INFO "}
{"@t":"2023-11-08T09:43:19.4718261Z","@mt":"Execute {MigrationType}","MigrationType":"InstallUmbracoForms","SourceContext":"Umbraco.Cms.Infrastructure.Migrations.MigrationPlanExecutor","ProcessId":8944,"ProcessName":"iisexpress","ThreadId":1,"ApplicationId":"3f3ed72a8d0f46228ba494c1a1aeb400115a9d84","MachineName":"IPS-025","Log4NetLevel":"INFO "}
{"@t":"2023-11-08T09:43:19.4880516Z","@mt":"Create table:\n {Sql}","Sql":"CREATE TABLE UFRecords\r\n(\r\n \"Id\" INTEGER NOT NULL PRIMARY KEY AUTOINCREMENT\r\n, \"Form\" TEXT NOT NULL\r\n, \"Created\" TEXT NOT NULL\r\n, \"Updated\" TEXT NOT NULL\r\n, \"CurrentPage\" TEXT NULL\r\n, \"UmbracoPageId\" INTEGER NULL\r\n, \"IP\" TEXT COLLATE NOCASE NULL\r\n, \"MemberKey\" TEXT COLLATE NOCASE NULL\r\n, \"UniqueId\" TEXT NOT NULL\r\n, \"State\" TEXT COLLATE NOCASE NULL\r\n, \"RecordData\" TEXT COLLATE NOCASE NOT NULL\r\n, \"Culture\" TEXT COLLATE NOCASE NULL\r\n, CONSTRAINT PK_UFRecords UNIQUE (\"Id\")\r\n)\r\n","SourceContext":"Umbraco.Cms.Persistence.Sqlite.Services.SqliteSyntaxProvider","ProcessId":8944,"ProcessName":"iisexpress","ThreadId":1,"ApplicationId":"3f3ed72a8d0f46228ba494c1a1aeb400115a9d84","MachineName":"IPS-025","Log4NetLevel":"INFO "}
{"@t":"2023-11-08T09:43:19.4936979Z","@mt":"Create table:\n {Sql}","Sql":"CREATE TABLE UFRecordFields\r\n(\r\n \"Key\" TEXT NOT NULL\r\n, \"FieldId\" TEXT NOT NULL\r\n, \"Record\" INTEGER NOT NULL\r\n, \"Alias\" TEXT COLLATE NOCASE NOT NULL\r\n, \"DataType\" TEXT COLLATE NOCASE NOT NULL\r\n, CONSTRAINT PK_UFRecordFields PRIMARY KEY (\"Key\")\r\n, CONSTRAINT FK_UFRecordFields_UFRecords_Id FOREIGN KEY (\"Record\") REFERENCES \"UFRecords\" (\"Id\")  \r\n)\r\n","SourceContext":"Umbraco.Cms.Persistence.Sqlite.Services.SqliteSyntaxProvider","ProcessId":8944,"ProcessName":"iisexpress","ThreadId":1,"ApplicationId":"3f3ed72a8d0f46228ba494c1a1aeb400115a9d84","MachineName":"IPS-025","Log4NetLevel":"INFO "}
{"@t":"2023-11-08T09:43:19.4967939Z","@mt":"Create Index:\n {Sql}","Sql":"CREATE  INDEX \"IX_record_recordfield\" ON \"UFRecordFields\" (\"Record\")","SourceContext":"Umbraco.Cms.Persistence.Sqlite.Services.SqliteSyntaxProvider","ProcessId":8944,"ProcessName":"iisexpress","ThreadId":1,"ApplicationId":"3f3ed72a8d0f46228ba494c1a1aeb400115a9d84","MachineName":"IPS-025","Log4NetLevel":"INFO "}
{"@t":"2023-11-08T09:43:19.4982313Z","@mt":"Create table:\n {Sql}","Sql":"CREATE TABLE UFRecordDataString\r\n(\r\n \"Id\" INTEGER NOT NULL PRIMARY KEY AUTOINCREMENT\r\n, \"Key\" TEXT NOT NULL\r\n, \"Value\" TEXT COLLATE NOCASE NOT NULL\r\n, CONSTRAINT PK_UFRecordDataString UNIQUE (\"Id\")\r\n, CONSTRAINT FK_UFRecordDataString_UFRecordFields_Key FOREIGN KEY (\"Key\") REFERENCES \"UFRecordFields\" (\"Key\")  \r\n)\r\n","SourceContext":"Umbraco.Cms.Persistence.Sqlite.Services.SqliteSyntaxProvider","ProcessId":8944,"ProcessName":"iisexpress","ThreadId":1,"ApplicationId":"3f3ed72a8d0f46228ba494c1a1aeb400115a9d84","MachineName":"IPS-025","Log4NetLevel":"INFO "}
{"@t":"2023-11-08T09:43:19.4986484Z","@mt":"Create Index:\n {Sql}","Sql":"CREATE  INDEX \"IX_datastring_recordfield\" ON \"UFRecordDataString\" (\"Key\")","SourceContext":"Umbraco.Cms.Persistence.Sqlite.Services.SqliteSyntaxProvider","ProcessId":8944,"ProcessName":"iisexpress","ThreadId":1,"ApplicationId":"3f3ed72a8d0f46228ba494c1a1aeb400115a9d84","MachineName":"IPS-025","Log4NetLevel":"INFO "}
{"@t":"2023-11-08T09:43:19.5003614Z","@mt":"Create table:\n {Sql}","Sql":"CREATE TABLE UFRecordDataLongString\r\n(\r\n \"Id\" INTEGER NOT NULL PRIMARY KEY AUTOINCREMENT\r\n, \"Key\" TEXT NOT NULL\r\n, \"Value\" TEXT COLLATE NOCASE NULL\r\n, CONSTRAINT PK_UFRecordDataLongString UNIQUE (\"Id\")\r\n, CONSTRAINT FK_UFRecordDataLongString_UFRecordFields_Key FOREIGN KEY (\"Key\") REFERENCES \"UFRecordFields\" (\"Key\")  \r\n)\r\n","SourceContext":"Umbraco.Cms.Persistence.Sqlite.Services.SqliteSyntaxProvider","ProcessId":8944,"ProcessName":"iisexpress","ThreadId":1,"ApplicationId":"3f3ed72a8d0f46228ba494c1a1aeb400115a9d84","MachineName":"IPS-025","Log4NetLevel":"INFO "}
{"@t":"2023-11-08T09:43:19.5009708Z","@mt":"Create Index:\n {Sql}","Sql":"CREATE  INDEX \"IX_datalongstring_recordfield\" ON \"UFRecordDataLongString\" (\"Key\")","SourceContext":"Umbraco.Cms.Persistence.Sqlite.Services.SqliteSyntaxProvider","ProcessId":8944,"ProcessName":"iisexpress","ThreadId":1,"ApplicationId":"3f3ed72a8d0f46228ba494c1a1aeb400115a9d84","MachineName":"IPS-025","Log4NetLevel":"INFO "}
{"@t":"2023-11-08T09:43:19.5027317Z","@mt":"Create table:\n {Sql}","Sql":"CREATE TABLE UFRecordDataInteger\r\n(\r\n \"Id\" INTEGER NOT NULL PRIMARY KEY AUTOINCREMENT\r\n, \"Key\" TEXT NOT NULL\r\n, \"Value\" INTEGER NULL\r\n, CONSTRAINT PK_UFRecordDataInteger UNIQUE (\"Id\")\r\n, CONSTRAINT FK_UFRecordDataInteger_UFRecordFields_Key FOREIGN KEY (\"Key\") REFERENCES \"UFRecordFields\" (\"Key\")  \r\n)\r\n","SourceContext":"Umbraco.Cms.Persistence.Sqlite.Services.SqliteSyntaxProvider","ProcessId":8944,"ProcessName":"iisexpress","ThreadId":1,"ApplicationId":"3f3ed72a8d0f46228ba494c1a1aeb400115a9d84","MachineName":"IPS-025","Log4NetLevel":"INFO "}
{"@t":"2023-11-08T09:43:19.5031031Z","@mt":"Create Index:\n {Sql}","Sql":"CREATE  INDEX \"IX_datainteger_recordfield\" ON \"UFRecordDataInteger\" (\"Key\")","SourceContext":"Umbraco.Cms.Persistence.Sqlite.Services.SqliteSyntaxProvider","ProcessId":8944,"ProcessName":"iisexpress","ThreadId":1,"ApplicationId":"3f3ed72a8d0f46228ba494c1a1aeb400115a9d84","MachineName":"IPS-025","Log4NetLevel":"INFO "}
{"@t":"2023-11-08T09:43:19.5038156Z","@mt":"Create table:\n {Sql}","Sql":"CREATE TABLE UFRecordDataBit\r\n(\r\n \"Id\" INTEGER NOT NULL PRIMARY KEY AUTOINCREMENT\r\n, \"Key\" TEXT NOT NULL\r\n, \"Value\" INTEGER NULL\r\n, CONSTRAINT PK_UFRecordDataBit UNIQUE (\"Id\")\r\n, CONSTRAINT FK_UFRecordDataBit_UFRecordFields_Key FOREIGN KEY (\"Key\") REFERENCES \"UFRecordFields\" (\"Key\")  \r\n)\r\n","SourceContext":"Umbraco.Cms.Persistence.Sqlite.Services.SqliteSyntaxProvider","ProcessId":8944,"ProcessName":"iisexpress","ThreadId":1,"ApplicationId":"3f3ed72a8d0f46228ba494c1a1aeb400115a9d84","MachineName":"IPS-025","Log4NetLevel":"INFO "}
{"@t":"2023-11-08T09:43:19.5041022Z","@mt":"Create Index:\n {Sql}","Sql":"CREATE  INDEX \"IX_databit_recordfield\" ON \"UFRecordDataBit\" (\"Key\")","SourceContext":"Umbraco.Cms.Persistence.Sqlite.Services.SqliteSyntaxProvider","ProcessId":8944,"ProcessName":"iisexpress","ThreadId":1,"ApplicationId":"3f3ed72a8d0f46228ba494c1a1aeb400115a9d84","MachineName":"IPS-025","Log4NetLevel":"INFO "}
{"@t":"2023-11-08T09:43:19.5047859Z","@mt":"Create table:\n {Sql}","Sql":"CREATE TABLE UFRecordDataDateTime\r\n(\r\n \"Id\" INTEGER NOT NULL PRIMARY KEY AUTOINCREMENT\r\n, \"Key\" TEXT NOT NULL\r\n, \"Value\" TEXT NULL\r\n, CONSTRAINT PK_UFRecordDataDateTime UNIQUE (\"Id\")\r\n, CONSTRAINT FK_UFRecordDataDateTime_UFRecordFields_Key FOREIGN KEY (\"Key\") REFERENCES \"UFRecordFields\" (\"Key\")  \r\n)\r\n","SourceContext":"Umbraco.Cms.Persistence.Sqlite.Services.SqliteSyntaxProvider","ProcessId":8944,"ProcessName":"iisexpress","ThreadId":1,"ApplicationId":"3f3ed72a8d0f46228ba494c1a1aeb400115a9d84","MachineName":"IPS-025","Log4NetLevel":"INFO "}
{"@t":"2023-11-08T09:43:19.5050790Z","@mt":"Create Index:\n {Sql}","Sql":"CREATE  INDEX \"IX_datadatetime_recordfield\" ON \"UFRecordDataDateTime\" (\"Key\")","SourceContext":"Umbraco.Cms.Persistence.Sqlite.Services.SqliteSyntaxProvider","ProcessId":8944,"ProcessName":"iisexpress","ThreadId":1,"ApplicationId":"3f3ed72a8d0f46228ba494c1a1aeb400115a9d84","MachineName":"IPS-025","Log4NetLevel":"INFO "}
{"@t":"2023-11-08T09:43:19.5062653Z","@mt":"Create table:\n {Sql}","Sql":"CREATE TABLE UFRecordAudit\r\n(\r\n \"Id\" INTEGER NOT NULL PRIMARY KEY AUTOINCREMENT\r\n, \"Record\" INTEGER NOT NULL\r\n, \"UpdatedOn\" TEXT NOT NULL\r\n, \"UpdatedBy\" INTEGER NULL\r\n, CONSTRAINT PK_UFRecordAudit UNIQUE (\"Id\")\r\n, CONSTRAINT FK_UFRecordAudit_UFRecords_Id FOREIGN KEY (\"Record\") REFERENCES \"UFRecords\" (\"Id\")  \r\n)\r\n","SourceContext":"Umbraco.Cms.Persistence.Sqlite.Services.SqliteSyntaxProvider","ProcessId":8944,"ProcessName":"iisexpress","ThreadId":1,"ApplicationId":"3f3ed72a8d0f46228ba494c1a1aeb400115a9d84","MachineName":"IPS-025","Log4NetLevel":"INFO "}
{"@t":"2023-11-08T09:43:19.5066119Z","@mt":"Create Index:\n {Sql}","Sql":"CREATE  INDEX \"IX_Record_RecordAudit\" ON \"UFRecordAudit\" (\"Record\")","SourceContext":"Umbraco.Cms.Persistence.Sqlite.Services.SqliteSyntaxProvider","ProcessId":8944,"ProcessName":"iisexpress","ThreadId":1,"ApplicationId":"3f3ed72a8d0f46228ba494c1a1aeb400115a9d84","MachineName":"IPS-025","Log4NetLevel":"INFO "}
{"@t":"2023-11-08T09:43:19.5073259Z","@mt":"Create Index:\n {Sql}","Sql":"CREATE  INDEX \"IX_Record_UpdatedBy\" ON \"UFRecordAudit\" (\"UpdatedBy\")","SourceContext":"Umbraco.Cms.Persistence.Sqlite.Services.SqliteSyntaxProvider","ProcessId":8944,"ProcessName":"iisexpress","ThreadId":1,"ApplicationId":"3f3ed72a8d0f46228ba494c1a1aeb400115a9d84","MachineName":"IPS-025","Log4NetLevel":"INFO "}
{"@t":"2023-11-08T09:43:19.5108592Z","@mt":"Create table:\n {Sql}","Sql":"CREATE TABLE UFFolders\r\n(\r\n \"ParentKey\" TEXT NULL\r\n, \"Id\" INTEGER NOT NULL PRIMARY KEY AUTOINCREMENT\r\n, \"Key\" TEXT NOT NULL\r\n, \"Name\" TEXT COLLATE NOCASE NOT NULL\r\n, \"Definition\" TEXT COLLATE NOCASE NOT NULL\r\n, \"Created\" TEXT NOT NULL\r\n, \"Updated\" TEXT NOT NULL\r\n, CONSTRAINT PK_UFFolders UNIQUE (\"Id\")\r\n, CONSTRAINT FK_UFFolders_UFFolders_Key FOREIGN KEY (\"ParentKey\") REFERENCES \"UFFolders\" (\"Key\")  \r\n)\r\n","SourceContext":"Umbraco.Cms.Persistence.Sqlite.Services.SqliteSyntaxProvider","ProcessId":8944,"ProcessName":"iisexpress","ThreadId":1,"ApplicationId":"3f3ed72a8d0f46228ba494c1a1aeb400115a9d84","MachineName":"IPS-025","Log4NetLevel":"INFO "}
{"@t":"2023-11-08T09:43:19.5139696Z","@mt":"Create Index:\n {Sql}","Sql":"CREATE UNIQUE INDEX \"IX_UFFolders_Key\" ON \"UFFolders\" (\"Key\")","SourceContext":"Umbraco.Cms.Persistence.Sqlite.Services.SqliteSyntaxProvider","ProcessId":8944,"ProcessName":"iisexpress","ThreadId":1,"ApplicationId":"3f3ed72a8d0f46228ba494c1a1aeb400115a9d84","MachineName":"IPS-025","Log4NetLevel":"INFO "}
{"@t":"2023-11-08T09:43:19.5157979Z","@mt":"Create table:\n {Sql}","Sql":"CREATE TABLE UFForms\r\n(\r\n \"FolderKey\" TEXT NULL\r\n, \"Id\" INTEGER NOT NULL PRIMARY KEY AUTOINCREMENT\r\n, \"Key\" TEXT NOT NULL\r\n, \"Name\" TEXT COLLATE NOCASE NOT NULL\r\n, \"Definition\" TEXT COLLATE NOCASE NOT NULL\r\n, \"Created\" TEXT NOT NULL\r\n, \"Updated\" TEXT NOT NULL\r\n, CONSTRAINT PK_UFForms UNIQUE (\"Id\")\r\n, CONSTRAINT FK_UFForms_UFFolders_Key FOREIGN KEY (\"FolderKey\") REFERENCES \"UFFolders\" (\"Key\")  \r\n)\r\n","SourceContext":"Umbraco.Cms.Persistence.Sqlite.Services.SqliteSyntaxProvider","ProcessId":8944,"ProcessName":"iisexpress","ThreadId":1,"ApplicationId":"3f3ed72a8d0f46228ba494c1a1aeb400115a9d84","MachineName":"IPS-025","Log4NetLevel":"INFO "}
{"@t":"2023-11-08T09:43:19.5161717Z","@mt":"Create Index:\n {Sql}","Sql":"CREATE UNIQUE INDEX \"IX_UFForms_Key\" ON \"UFForms\" (\"Key\")","SourceContext":"Umbraco.Cms.Persistence.Sqlite.Services.SqliteSyntaxProvider","ProcessId":8944,"ProcessName":"iisexpress","ThreadId":1,"ApplicationId":"3f3ed72a8d0f46228ba494c1a1aeb400115a9d84","MachineName":"IPS-025","Log4NetLevel":"INFO "}
{"@t":"2023-11-08T09:43:19.5169326Z","@mt":"Create table:\n {Sql}","Sql":"CREATE TABLE UFWorkflows\r\n(\r\n \"FormId\" TEXT NOT NULL\r\n, \"Id\" INTEGER NOT NULL PRIMARY KEY AUTOINCREMENT\r\n, \"Key\" TEXT NOT NULL\r\n, \"Name\" TEXT COLLATE NOCASE NOT NULL\r\n, \"Definition\" TEXT COLLATE NOCASE NOT NULL\r\n, \"Created\" TEXT NOT NULL\r\n, \"Updated\" TEXT NOT NULL\r\n, CONSTRAINT PK_UFWorkflows UNIQUE (\"Id\")\r\n)\r\n","SourceContext":"Umbraco.Cms.Persistence.Sqlite.Services.SqliteSyntaxProvider","ProcessId":8944,"ProcessName":"iisexpress","ThreadId":1,"ApplicationId":"3f3ed72a8d0f46228ba494c1a1aeb400115a9d84","MachineName":"IPS-025","Log4NetLevel":"INFO "}
{"@t":"2023-11-08T09:43:19.5172412Z","@mt":"Create Index:\n {Sql}","Sql":"CREATE  INDEX \"IX_UFWorkflows_FormId\" ON \"UFWorkflows\" (\"FormId\")","SourceContext":"Umbraco.Cms.Persistence.Sqlite.Services.SqliteSyntaxProvider","ProcessId":8944,"ProcessName":"iisexpress","ThreadId":1,"ApplicationId":"3f3ed72a8d0f46228ba494c1a1aeb400115a9d84","MachineName":"IPS-025","Log4NetLevel":"INFO "}
{"@t":"2023-11-08T09:43:19.5179259Z","@mt":"Create Index:\n {Sql}","Sql":"CREATE UNIQUE INDEX \"IX_UFWorkflows_Key\" ON \"UFWorkflows\" (\"Key\")","SourceContext":"Umbraco.Cms.Persistence.Sqlite.Services.SqliteSyntaxProvider","ProcessId":8944,"ProcessName":"iisexpress","ThreadId":1,"ApplicationId":"3f3ed72a8d0f46228ba494c1a1aeb400115a9d84","MachineName":"IPS-025","Log4NetLevel":"INFO "}
{"@t":"2023-11-08T09:43:19.5197232Z","@mt":"Create table:\n {Sql}","Sql":"CREATE TABLE UFPrevalueSource\r\n(\r\n \"Id\" INTEGER NOT NULL PRIMARY KEY AUTOINCREMENT\r\n, \"Key\" TEXT NOT NULL\r\n, \"Name\" TEXT COLLATE NOCASE NOT NULL\r\n, \"Definition\" TEXT COLLATE NOCASE NOT NULL\r\n, \"Created\" TEXT NOT NULL\r\n, \"Updated\" TEXT NOT NULL\r\n, CONSTRAINT PK_UFPrevalueSource UNIQUE (\"Id\")\r\n)\r\n","SourceContext":"Umbraco.Cms.Persistence.Sqlite.Services.SqliteSyntaxProvider","ProcessId":8944,"ProcessName":"iisexpress","ThreadId":1,"ApplicationId":"3f3ed72a8d0f46228ba494c1a1aeb400115a9d84","MachineName":"IPS-025","Log4NetLevel":"INFO "}
{"@t":"2023-11-08T09:43:19.5205143Z","@mt":"Create Index:\n {Sql}","Sql":"CREATE UNIQUE INDEX \"IX_UFPrevalueSource_Key\" ON \"UFPrevalueSource\" (\"Key\")","SourceContext":"Umbraco.Cms.Persistence.Sqlite.Services.SqliteSyntaxProvider","ProcessId":8944,"ProcessName":"iisexpress","ThreadId":1,"ApplicationId":"3f3ed72a8d0f46228ba494c1a1aeb400115a9d84","MachineName":"IPS-025","Log4NetLevel":"INFO "}
{"@t":"2023-11-08T09:43:19.5213714Z","@mt":"Create table:\n {Sql}","Sql":"CREATE TABLE UFDataSource\r\n(\r\n \"Id\" INTEGER NOT NULL PRIMARY KEY AUTOINCREMENT\r\n, \"Key\" TEXT NOT NULL\r\n, \"Name\" TEXT COLLATE NOCASE NOT NULL\r\n, \"Definition\" TEXT COLLATE NOCASE NOT NULL\r\n, \"Created\" TEXT NOT NULL\r\n, \"Updated\" TEXT NOT NULL\r\n, CONSTRAINT PK_UFDataSource UNIQUE (\"Id\")\r\n)\r\n","SourceContext":"Umbraco.Cms.Persistence.Sqlite.Services.SqliteSyntaxProvider","ProcessId":8944,"ProcessName":"iisexpress","ThreadId":1,"ApplicationId":"3f3ed72a8d0f46228ba494c1a1aeb400115a9d84","MachineName":"IPS-025","Log4NetLevel":"INFO "}
{"@t":"2023-11-08T09:43:19.5216891Z","@mt":"Create Index:\n {Sql}","Sql":"CREATE UNIQUE INDEX \"IX_UFDataSource_Key\" ON \"UFDataSource\" (\"Key\")","SourceContext":"Umbraco.Cms.Persistence.Sqlite.Services.SqliteSyntaxProvider","ProcessId":8944,"ProcessName":"iisexpress","ThreadId":1,"ApplicationId":"3f3ed72a8d0f46228ba494c1a1aeb400115a9d84","MachineName":"IPS-025","Log4NetLevel":"INFO "}
{"@t":"2023-11-08T09:43:19.5236122Z","@mt":"Create table:\n {Sql}","Sql":"CREATE TABLE UFUserSecurity\r\n(\r\n \"User\" TEXT COLLATE NOCASE NOT NULL\r\n, \"ManageDataSources\" INTEGER NOT NULL\r\n, \"ManagePreValueSources\" INTEGER NOT NULL\r\n, \"ManageWorkflows\" INTEGER NOT NULL\r\n, \"ManageForms\" INTEGER NOT NULL\r\n, \"ViewEntries\" INTEGER NOT NULL CONSTRAINT \"DF_UFUserSecurity_ViewEntries\" DEFAULT ('0')\r\n, \"EditEntries\" INTEGER NOT NULL CONSTRAINT \"DF_UFUserSecurity_EditEntries\" DEFAULT ('0')\r\n, CONSTRAINT PK_UFUserSecurity PRIMARY KEY (\"User\")\r\n)\r\n","SourceContext":"Umbraco.Cms.Persistence.Sqlite.Services.SqliteSyntaxProvider","ProcessId":8944,"ProcessName":"iisexpress","ThreadId":1,"ApplicationId":"3f3ed72a8d0f46228ba494c1a1aeb400115a9d84","MachineName":"IPS-025","Log4NetLevel":"INFO "}
{"@t":"2023-11-08T09:43:19.5259649Z","@mt":"Create table:\n {Sql}","Sql":"CREATE TABLE UFUserFormSecurity\r\n(\r\n \"Id\" INTEGER NOT NULL PRIMARY KEY AUTOINCREMENT\r\n, \"User\" TEXT COLLATE NOCASE NOT NULL\r\n, \"Form\" TEXT NOT NULL\r\n, \"HasAccess\" INTEGER NOT NULL\r\n, \"AllowInEditor\" INTEGER NOT NULL\r\n, \"SecurityType\" INTEGER NOT NULL\r\n, CONSTRAINT PK_UFUserFormSecurity UNIQUE (\"Id\")\r\n, CONSTRAINT FK_UFUserFormSecurity_UFForms_Key FOREIGN KEY (\"Form\") REFERENCES \"UFForms\" (\"Key\")  \r\n)\r\n","SourceContext":"Umbraco.Cms.Persistence.Sqlite.Services.SqliteSyntaxProvider","ProcessId":8944,"ProcessName":"iisexpress","ThreadId":1,"ApplicationId":"3f3ed72a8d0f46228ba494c1a1aeb400115a9d84","MachineName":"IPS-025","Log4NetLevel":"INFO "}
{"@t":"2023-11-08T09:43:19.5299714Z","@mt":"Create Index:\n {Sql}","Sql":"CREATE UNIQUE INDEX \"IX_UFUserFormSecurity_User_Form\" ON \"UFUserFormSecurity\" (\"User\",\"Form\")","SourceContext":"Umbraco.Cms.Persistence.Sqlite.Services.SqliteSyntaxProvider","ProcessId":8944,"ProcessName":"iisexpress","ThreadId":1,"ApplicationId":"3f3ed72a8d0f46228ba494c1a1aeb400115a9d84","MachineName":"IPS-025","Log4NetLevel":"INFO "}
{"@t":"2023-11-08T09:43:19.5323562Z","@mt":"Create table:\n {Sql}","Sql":"CREATE TABLE UFUserGroupSecurity\r\n(\r\n \"UserGroupId\" INTEGER NOT NULL\r\n, \"ManageDataSources\" INTEGER NOT NULL\r\n, \"ManagePreValueSources\" INTEGER NOT NULL\r\n, \"ManageWorkflows\" INTEGER NOT NULL\r\n, \"ManageForms\" INTEGER NOT NULL\r\n, \"ViewEntries\" INTEGER NOT NULL CONSTRAINT \"DF_UFUserGroupSecurity_ViewEntries\" DEFAULT ('0')\r\n, \"EditEntries\" INTEGER NOT NULL CONSTRAINT \"DF_UFUserGroupSecurity_EditEntries\" DEFAULT ('0')\r\n, CONSTRAINT PK_UFUserGroupSecurity PRIMARY KEY (\"UserGroupId\")\r\n)\r\n","SourceContext":"Umbraco.Cms.Persistence.Sqlite.Services.SqliteSyntaxProvider","ProcessId":8944,"ProcessName":"iisexpress","ThreadId":1,"ApplicationId":"3f3ed72a8d0f46228ba494c1a1aeb400115a9d84","MachineName":"IPS-025","Log4NetLevel":"INFO "}
{"@t":"2023-11-08T09:43:19.5348368Z","@mt":"Create table:\n {Sql}","Sql":"CREATE TABLE UFUserGroupFormSecurity\r\n(\r\n \"Id\" INTEGER NOT NULL PRIMARY KEY AUTOINCREMENT\r\n, \"UserGroupId\" INTEGER NOT NULL\r\n, \"Form\" TEXT NOT NULL\r\n, \"HasAccess\" INTEGER NOT NULL\r\n, \"AllowInEditor\" INTEGER NOT NULL\r\n, \"SecurityType\" INTEGER NOT NULL\r\n, CONSTRAINT PK_UFUserGroupFormSecurity UNIQUE (\"Id\")\r\n, CONSTRAINT FK_UFUserGroupFormSecurity_UFForms_Key FOREIGN KEY (\"Form\") REFERENCES \"UFForms\" (\"Key\")  \r\n)\r\n","SourceContext":"Umbraco.Cms.Persistence.Sqlite.Services.SqliteSyntaxProvider","ProcessId":8944,"ProcessName":"iisexpress","ThreadId":1,"ApplicationId":"3f3ed72a8d0f46228ba494c1a1aeb400115a9d84","MachineName":"IPS-025","Log4NetLevel":"INFO "}
{"@t":"2023-11-08T09:43:19.5354703Z","@mt":"Create Index:\n {Sql}","Sql":"CREATE UNIQUE INDEX \"IX_UFUserGroupFormSecurity_UserGroupId_Form\" ON \"UFUserGroupFormSecurity\" (\"UserGroupId\",\"Form\")","SourceContext":"Umbraco.Cms.Persistence.Sqlite.Services.SqliteSyntaxProvider","ProcessId":8944,"ProcessName":"iisexpress","ThreadId":1,"ApplicationId":"3f3ed72a8d0f46228ba494c1a1aeb400115a9d84","MachineName":"IPS-025","Log4NetLevel":"INFO "}
{"@t":"2023-11-08T09:43:19.5363987Z","@mt":"Create table:\n {Sql}","Sql":"CREATE TABLE UFUserStartFolders\r\n(\r\n \"UserId\" INTEGER NOT NULL\r\n, \"FolderKey\" TEXT NOT NULL\r\n, CONSTRAINT PK_UFUserStartFolders PRIMARY KEY (\"UserId\", \"FolderKey\")\r\n, CONSTRAINT FK_UFUserStartFolders_UFFolders_Key FOREIGN KEY (\"FolderKey\") REFERENCES \"UFFolders\" (\"Key\")  \r\n)\r\n","SourceContext":"Umbraco.Cms.Persistence.Sqlite.Services.SqliteSyntaxProvider","ProcessId":8944,"ProcessName":"iisexpress","ThreadId":1,"ApplicationId":"3f3ed72a8d0f46228ba494c1a1aeb400115a9d84","MachineName":"IPS-025","Log4NetLevel":"INFO "}
{"@t":"2023-11-08T09:43:19.5367450Z","@mt":"Create Index:\n {Sql}","Sql":"CREATE  INDEX \"IX_UserStartFolder_UserId\" ON \"UFUserStartFolders\" (\"UserId\")","SourceContext":"Umbraco.Cms.Persistence.Sqlite.Services.SqliteSyntaxProvider","ProcessId":8944,"ProcessName":"iisexpress","ThreadId":1,"ApplicationId":"3f3ed72a8d0f46228ba494c1a1aeb400115a9d84","MachineName":"IPS-025","Log4NetLevel":"INFO "}
{"@t":"2023-11-08T09:43:19.5370368Z","@mt":"Create Index:\n {Sql}","Sql":"CREATE  INDEX \"IX_UserStartFolder_FolderKey\" ON \"UFUserStartFolders\" (\"FolderKey\")","SourceContext":"Umbraco.Cms.Persistence.Sqlite.Services.SqliteSyntaxProvider","ProcessId":8944,"ProcessName":"iisexpress","ThreadId":1,"ApplicationId":"3f3ed72a8d0f46228ba494c1a1aeb400115a9d84","MachineName":"IPS-025","Log4NetLevel":"INFO "}
{"@t":"2023-11-08T09:43:19.5377777Z","@mt":"Create table:\n {Sql}","Sql":"CREATE TABLE UFUserGroupStartFolders\r\n(\r\n \"UserGroupId\" INTEGER NOT NULL\r\n, \"FolderKey\" TEXT NOT NULL\r\n, CONSTRAINT PK_UFUserGroupStartFolders PRIMARY KEY (\"UserGroupId\", \"FolderKey\")\r\n, CONSTRAINT FK_UFUserGroupStartFolders_UFFolders_Key FOREIGN KEY (\"FolderKey\") REFERENCES \"UFFolders\" (\"Key\")  \r\n)\r\n","SourceContext":"Umbraco.Cms.Persistence.Sqlite.Services.SqliteSyntaxProvider","ProcessId":8944,"ProcessName":"iisexpress","ThreadId":1,"ApplicationId":"3f3ed72a8d0f46228ba494c1a1aeb400115a9d84","MachineName":"IPS-025","Log4NetLevel":"INFO "}
{"@t":"2023-11-08T09:43:19.5380911Z","@mt":"Create Index:\n {Sql}","Sql":"CREATE  INDEX \"IX_UserGroupStartFolder_UserGroupId\" ON \"UFUserGroupStartFolders\" (\"UserGroupId\")","SourceContext":"Umbraco.Cms.Persistence.Sqlite.Services.SqliteSyntaxProvider","ProcessId":8944,"ProcessName":"iisexpress","ThreadId":1,"ApplicationId":"3f3ed72a8d0f46228ba494c1a1aeb400115a9d84","MachineName":"IPS-025","Log4NetLevel":"INFO "}
{"@t":"2023-11-08T09:43:19.5383577Z","@mt":"Create Index:\n {Sql}","Sql":"CREATE  INDEX \"IX_UserGroupStartFolder_FolderKey\" ON \"UFUserGroupStartFolders\" (\"FolderKey\")","SourceContext":"Umbraco.Cms.Persistence.Sqlite.Services.SqliteSyntaxProvider","ProcessId":8944,"ProcessName":"iisexpress","ThreadId":1,"ApplicationId":"3f3ed72a8d0f46228ba494c1a1aeb400115a9d84","MachineName":"IPS-025","Log4NetLevel":"INFO "}
{"@t":"2023-11-08T09:43:21.5655843Z","@mt":"At {OrigState}","OrigState":"7c7bc5ee-4c5b-42dc-9576-5ce6dfbddb8e","SourceContext":"Umbraco.Cms.Infrastructure.Migrations.MigrationPlanExecutor","ProcessId":8944,"ProcessName":"iisexpress","ThreadId":1,"ApplicationId":"3f3ed72a8d0f46228ba494c1a1aeb400115a9d84","MachineName":"IPS-025","Log4NetLevel":"INFO "}
{"@t":"2023-11-08T09:43:21.5656300Z","@mt":"Execute {MigrationType}","MigrationType":"AddRecordCultureColumn","SourceContext":"Umbraco.Cms.Infrastructure.Migrations.MigrationPlanExecutor","ProcessId":8944,"ProcessName":"iisexpress","ThreadId":1,"ApplicationId":"3f3ed72a8d0f46228ba494c1a1aeb400115a9d84","MachineName":"IPS-025","Log4NetLevel":"INFO "}
{"@t":"2023-11-08T09:43:21.5847526Z","@mt":"At {OrigState}","OrigState":"9f7e6fe6-bbd5-4b2b-8820-e9e0e36cc74c","SourceContext":"Umbraco.Cms.Infrastructure.Migrations.MigrationPlanExecutor","ProcessId":8944,"ProcessName":"iisexpress","ThreadId":1,"ApplicationId":"3f3ed72a8d0f46228ba494c1a1aeb400115a9d84","MachineName":"IPS-025","Log4NetLevel":"INFO "}
{"@t":"2023-11-08T09:43:21.5847947Z","@mt":"Execute {MigrationType}","MigrationType":"AddRecordWorkflowAudit","SourceContext":"Umbraco.Cms.Infrastructure.Migrations.MigrationPlanExecutor","ProcessId":8944,"ProcessName":"iisexpress","ThreadId":1,"ApplicationId":"3f3ed72a8d0f46228ba494c1a1aeb400115a9d84","MachineName":"IPS-025","Log4NetLevel":"INFO "}
{"@t":"2023-11-08T09:43:21.5861271Z","@mt":"Create table:\n {Sql}","Sql":"CREATE TABLE UFRecordWorkflowAudit\r\n(\r\n \"Id\" INTEGER NOT NULL PRIMARY KEY AUTOINCREMENT\r\n, \"RecordUniqueId\" TEXT NOT NULL\r\n, \"WorkflowKey\" TEXT NOT NULL\r\n, \"WorkflowName\" TEXT COLLATE NOCASE NOT NULL\r\n, \"WorkflowTypeId\" TEXT NOT NULL\r\n, \"WorkflowTypeName\" TEXT COLLATE NOCASE NOT NULL\r\n, \"ExecutedOn\" TEXT NOT NULL\r\n, \"ExecutionStage\" INTEGER NULL\r\n, \"ExecutionStatus\" INTEGER NOT NULL\r\n, CONSTRAINT PK_UFRecordWorkflowAudit UNIQUE (\"Id\")\r\n)\r\n","SourceContext":"Umbraco.Cms.Persistence.Sqlite.Services.SqliteSyntaxProvider","ProcessId":8944,"ProcessName":"iisexpress","ThreadId":1,"ApplicationId":"3f3ed72a8d0f46228ba494c1a1aeb400115a9d84","MachineName":"IPS-025","Log4NetLevel":"INFO "}
{"@t":"2023-11-08T09:43:21.5865884Z","@mt":"Create Index:\n {Sql}","Sql":"CREATE  INDEX \"IX_RecordUniqueId_RecordWorkflowAudit\" ON \"UFRecordWorkflowAudit\" (\"RecordUniqueId\")","SourceContext":"Umbraco.Cms.Persistence.Sqlite.Services.SqliteSyntaxProvider","ProcessId":8944,"ProcessName":"iisexpress","ThreadId":1,"ApplicationId":"3f3ed72a8d0f46228ba494c1a1aeb400115a9d84","MachineName":"IPS-025","Log4NetLevel":"INFO "}
{"@t":"2023-11-08T09:43:21.5870016Z","@mt":"Create Index:\n {Sql}","Sql":"CREATE  INDEX \"IX_WorkflowKey_RecordWorkflowAudit\" ON \"UFRecordWorkflowAudit\" (\"WorkflowKey\")","SourceContext":"Umbraco.Cms.Persistence.Sqlite.Services.SqliteSyntaxProvider","ProcessId":8944,"ProcessName":"iisexpress","ThreadId":1,"ApplicationId":"3f3ed72a8d0f46228ba494c1a1aeb400115a9d84","MachineName":"IPS-025","Log4NetLevel":"INFO "}
{"@t":"2023-11-08T09:43:21.5908568Z","@mt":"At {OrigState}","OrigState":"1a8f0d04-9396-40a2-9423-39fc9ae3828f","SourceContext":"Umbraco.Cms.Infrastructure.Migrations.MigrationPlanExecutor","ProcessId":8944,"ProcessName":"iisexpress","ThreadId":1,"ApplicationId":"3f3ed72a8d0f46228ba494c1a1aeb400115a9d84","MachineName":"IPS-025","Log4NetLevel":"INFO "}
{"@t":"2023-11-08T09:43:21.5909078Z","@mt":"Execute {MigrationType}","MigrationType":"AddRecordWorkflowAuditExecutionStage","SourceContext":"Umbraco.Cms.Infrastructure.Migrations.MigrationPlanExecutor","ProcessId":8944,"ProcessName":"iisexpress","ThreadId":1,"ApplicationId":"3f3ed72a8d0f46228ba494c1a1aeb400115a9d84","MachineName":"IPS-025","Log4NetLevel":"INFO "}
{"@t":"2023-11-08T09:43:21.6100067Z","@mt":"At {OrigState}","OrigState":"6e692c5d-c670-4c34-af17-28d8dbf0dcd2","SourceContext":"Umbraco.Cms.Infrastructure.Migrations.MigrationPlanExecutor","ProcessId":8944,"ProcessName":"iisexpress","ThreadId":1,"ApplicationId":"3f3ed72a8d0f46228ba494c1a1aeb400115a9d84","MachineName":"IPS-025","Log4NetLevel":"INFO "}
{"@t":"2023-11-08T09:43:21.6100556Z","@mt":"Execute {MigrationType}","MigrationType":"NoopMigration","SourceContext":"Umbraco.Cms.Infrastructure.Migrations.MigrationPlanExecutor","ProcessId":8944,"ProcessName":"iisexpress","ThreadId":1,"ApplicationId":"3f3ed72a8d0f46228ba494c1a1aeb400115a9d84","MachineName":"IPS-025","Log4NetLevel":"INFO "}
{"@t":"2023-11-08T09:43:21.6106555Z","@mt":"At {OrigState}","OrigState":"5d84fee1-388c-4e5f-b98c-1e66947278f1","SourceContext":"Umbraco.Cms.Infrastructure.Migrations.MigrationPlanExecutor","ProcessId":8944,"ProcessName":"iisexpress","ThreadId":1,"ApplicationId":"3f3ed72a8d0f46228ba494c1a1aeb400115a9d84","MachineName":"IPS-025","Log4NetLevel":"INFO "}
{"@t":"2023-11-08T09:43:21.6107099Z","@mt":"Done","SourceContext":"Umbraco.Cms.Infrastructure.Migrations.MigrationPlanExecutor","ProcessId":8944,"ProcessName":"iisexpress","ThreadId":1,"ApplicationId":"3f3ed72a8d0f46228ba494c1a1aeb400115a9d84","MachineName":"IPS-025","Log4NetLevel":"INFO "}
{"@t":"2023-11-08T09:43:21.6270447Z","@mt":"{EndMessage} ({Duration}ms) [Timing {TimingId}]","EndMessage":"Unattended upgrade completed for UmbracoForms","Duration":2184,"TimingId":"74d5146","SourceContext":"Umbraco.Cms.Core.Logging.ProfilingLogger","ProcessId":8944,"ProcessName":"iisexpress","ThreadId":1,"ApplicationId":"3f3ed72a8d0f46228ba494c1a1aeb400115a9d84","MachineName":"IPS-025","Log4NetLevel":"INFO "}
{"@t":"2023-11-08T09:43:22.6351266Z","@mt":"Application started. Press Ctrl+C to shut down.","SourceContext":"Microsoft.Hosting.Lifetime","ProcessId":8944,"ProcessName":"iisexpress","ThreadId":1,"ApplicationId":"3f3ed72a8d0f46228ba494c1a1aeb400115a9d84","MachineName":"IPS-025","Log4NetLevel":"INFO "}
{"@t":"2023-11-08T09:43:22.6351912Z","@mt":"Hosting environment: {EnvName}","EnvName":"Development","SourceContext":"Microsoft.Hosting.Lifetime","ProcessId":8944,"ProcessName":"iisexpress","ThreadId":1,"ApplicationId":"3f3ed72a8d0f46228ba494c1a1aeb400115a9d84","MachineName":"IPS-025","Log4NetLevel":"INFO "}
{"@t":"2023-11-08T09:43:22.6352095Z","@mt":"Content root path: {ContentRoot}","ContentRoot":"D:\\UmbracoProject\\UmbracoProjectDemo","SourceContext":"Microsoft.Hosting.Lifetime","ProcessId":8944,"ProcessName":"iisexpress","ThreadId":1,"ApplicationId":"3f3ed72a8d0f46228ba494c1a1aeb400115a9d84","MachineName":"IPS-025","Log4NetLevel":"INFO "}
{"@t":"2023-11-08T09:43:23.0100016Z","@mt":"Registered with MainDom, localContentDbExists? {LocalContentDbExists}, localMediaDbExists? {LocalMediaDbExists}","LocalContentDbExists":true,"LocalMediaDbExists":true,"SourceContext":"Umbraco.Cms.Infrastructure.PublishedCache.PublishedSnapshotService","RequestId":"80000064-0002-fb00-b63f-84710c7967bb","RequestPath":"/","ProcessId":8944,"ProcessName":"iisexpress","ThreadId":4,"ApplicationId":"3f3ed72a8d0f46228ba494c1a1aeb400115a9d84","MachineName":"IPS-025","Log4NetLevel":"INFO ","HttpRequestId":"a0859afa-1519-4378-858f-8f12d9f00124","HttpRequestNumber":1,"HttpSessionId":"0"}
{"@t":"2023-11-08T09:43:23.0148212Z","@mt":"Creating the content store, localContentDbExists? {LocalContentDbExists}","LocalContentDbExists":true,"SourceContext":"Umbraco.Cms.Infrastructure.PublishedCache.PublishedSnapshotService","RequestId":"80000064-0002-fb00-b63f-84710c7967bb","RequestPath":"/","ProcessId":8944,"ProcessName":"iisexpress","ThreadId":4,"ApplicationId":"3f3ed72a8d0f46228ba494c1a1aeb400115a9d84","MachineName":"IPS-025","Log4NetLevel":"INFO ","HttpRequestId":"a0859afa-1519-4378-858f-8f12d9f00124","HttpRequestNumber":1,"HttpSessionId":"0"}
{"@t":"2023-11-08T09:43:23.0168745Z","@mt":"Creating the media store, localMediaDbExists? {LocalMediaDbExists}","LocalMediaDbExists":true,"SourceContext":"Umbraco.Cms.Infrastructure.PublishedCache.PublishedSnapshotService","RequestId":"80000064-0002-fb00-b63f-84710c7967bb","RequestPath":"/","ProcessId":8944,"ProcessName":"iisexpress","ThreadId":4,"ApplicationId":"3f3ed72a8d0f46228ba494c1a1aeb400115a9d84","MachineName":"IPS-025","Log4NetLevel":"INFO ","HttpRequestId":"a0859afa-1519-4378-858f-8f12d9f00124","HttpRequestNumber":1,"HttpSessionId":"0"}
{"@t":"2023-11-08T09:43:23.6234727Z","@mt":"{StartMessage} [Timing {TimingId}]","StartMessage":"Loading content from local cache file","TimingId":"77bbbcf","SourceContext":"Umbraco.Cms.Core.Logging.ProfilingLogger","RequestId":"80000064-0002-fb00-b63f-84710c7967bb","RequestPath":"/","ProcessId":8944,"ProcessName":"iisexpress","ThreadId":4,"ApplicationId":"3f3ed72a8d0f46228ba494c1a1aeb400115a9d84","MachineName":"IPS-025","Log4NetLevel":"INFO ","HttpRequestId":"a0859afa-1519-4378-858f-8f12d9f00124","HttpRequestNumber":1,"HttpSessionId":"0"}
{"@t":"2023-11-08T09:43:23.6489751Z","@mt":"{EndMessage} ({Duration}ms) [Timing {TimingId}]","EndMessage":"Completed.","Duration":25,"TimingId":"77bbbcf","SourceContext":"Umbraco.Cms.Core.Logging.ProfilingLogger","RequestId":"80000064-0002-fb00-b63f-84710c7967bb","RequestPath":"/","ProcessId":8944,"ProcessName":"iisexpress","ThreadId":4,"ApplicationId":"3f3ed72a8d0f46228ba494c1a1aeb400115a9d84","MachineName":"IPS-025","Log4NetLevel":"INFO ","HttpRequestId":"a0859afa-1519-4378-858f-8f12d9f00124","HttpRequestNumber":1,"HttpSessionId":"0"}
{"@t":"2023-11-08T09:43:23.6559844Z","@mt":"{StartMessage} [Timing {TimingId}]","StartMessage":"Loading media from local cache file","TimingId":"b15d443","SourceContext":"Umbraco.Cms.Core.Logging.ProfilingLogger","RequestId":"80000064-0002-fb00-b63f-84710c7967bb","RequestPath":"/","ProcessId":8944,"ProcessName":"iisexpress","ThreadId":4,"ApplicationId":"3f3ed72a8d0f46228ba494c1a1aeb400115a9d84","MachineName":"IPS-025","Log4NetLevel":"INFO ","HttpRequestId":"a0859afa-1519-4378-858f-8f12d9f00124","HttpRequestNumber":1,"HttpSessionId":"0"}
{"@t":"2023-11-08T09:43:23.6569363Z","@mt":"{EndMessage} ({Duration}ms) [Timing {TimingId}]","EndMessage":"Completed.","Duration":0,"TimingId":"b15d443","SourceContext":"Umbraco.Cms.Core.Logging.ProfilingLogger","RequestId":"80000064-0002-fb00-b63f-84710c7967bb","RequestPath":"/","ProcessId":8944,"ProcessName":"iisexpress","ThreadId":4,"ApplicationId":"3f3ed72a8d0f46228ba494c1a1aeb400115a9d84","MachineName":"IPS-025","Log4NetLevel":"INFO ","HttpRequestId":"a0859afa-1519-4378-858f-8f12d9f00124","HttpRequestNumber":1,"HttpSessionId":"0"}
{"@t":"2023-11-08T09:44:23.8503754Z","@mt":"The Delivery API is not enabled, no indexing will performed for the Delivery API content index.","SourceContext":"Umbraco.Cms.Infrastructure.Examine.DeliveryApiContentIndexPopulator","ProcessId":8944,"ProcessName":"iisexpress","ThreadId":8,"ApplicationId":"3f3ed72a8d0f46228ba494c1a1aeb400115a9d84","MachineName":"IPS-025","Log4NetLevel":"INFO "}
{"@t":"2023-11-08T09:46:21.7482957Z","@mt":"Umbraco Forms scheduled record deletion task will not run as it has been not enabled via configuration. To enable, set the configuration value at 'Umbraco:Forms:Options:ScheduledRecordDeletion:Enabled' to true.","SourceContext":"Umbraco.Forms.Core.HostedServices.ScheduledRecordDeletion","ProcessId":8944,"ProcessName":"iisexpress","ThreadId":4,"ApplicationId":"3f3ed72a8d0f46228ba494c1a1aeb400115a9d84","MachineName":"IPS-025","Log4NetLevel":"INFO "}
{"@t":"2023-11-08T09:46:21.8053285Z","@mt":"Deleted {count} ContentVersion(s)","count":5,"SourceContext":"Umbraco.Cms.Infrastructure.HostedServices.ContentVersionCleanup","ProcessId":8944,"ProcessName":"iisexpress","ThreadId":6,"ApplicationId":"3f3ed72a8d0f46228ba494c1a1aeb400115a9d84","MachineName":"IPS-025","Log4NetLevel":"INFO "}
{"@t":"2023-11-08T09:51:45.4683383Z","@mt":"Exception ({InstanceId}).","@l":"Error","@x":"Microsoft.Data.Sqlite.SqliteException (0x80004005): SQLite Error 19: 'UNIQUE constraint failed: UFUserSecurity.User'.\r\n   at Microsoft.Data.Sqlite.SqliteException.ThrowExceptionForRC(Int32 rc, sqlite3 db)\r\n   at Microsoft.Data.Sqlite.SqliteDataReader.NextResult()\r\n   at Microsoft.Data.Sqlite.SqliteCommand.ExecuteReader(CommandBehavior behavior)\r\n   at Microsoft.Data.Sqlite.SqliteCommand.ExecuteNonQuery()\r\n   at Umbraco.Cms.Infrastructure.Persistence.FaultHandling.RetryPolicy.ExecuteAction[TResult](Func`1 func)\r\n   at NPoco.Database.ExecuteNonQueryHelper(DbCommand cmd)\r\n   at NPoco.Database.InsertAsyncImp[T](PocoData pocoData, String tableName, String primaryKeyName, Boolean autoIncrement, T poco, Boolean sync)\r\n   at NPoco.AsyncHelper.RunSync[T](Task`1 task)\r\n   at NPoco.Database.Insert[T](String tableName, String primaryKeyName, Boolean autoIncrement, T poco)\r\n   at NPoco.Database.Insert[T](T poco)\r\n   at Umbraco.Forms.Data.Storage.UserSecurityStorage.InsertUserSecurity(UserSecurity usersecurity)\r\n   at Umbraco.Forms.Core.Security.FormsSecurity.EnsureUserExists(IUser user)\r\n   at Umbraco.Forms.Core.Security.FormsSecurity.DoesUserHavePermission(IUser user, Func`2 permission, Boolean allowForAdmin, Boolean createUserSecurityRecordIfNotExists)\r\n   at Umbraco.Forms.Core.Security.FormsSecurity.DoesCurrentUserHavePermission(Func`2 permission, Boolean allowForAdmin, Boolean createUserSecurityRecordIfNotExists)\r\n   at Umbraco.Forms.Core.Security.FormsSecurity.CanCurrentUserManageForms()\r\n   at Umbraco.Forms.Web.Editors.FormControllerBase.GetAllFormsForCurrentUserSlim()\r\n   at lambda_method836(Closure, Object, Object[])\r\n   at Microsoft.AspNetCore.Mvc.Infrastructure.ActionMethodExecutor.SyncObjectResultExecutor.Execute(ActionContext actionContext, IActionResultTypeMapper mapper, ObjectMethodExecutor executor, Object controller, Object[] arguments)\r\n   at Microsoft.AspNetCore.Mvc.Infrastructure.ControllerActionInvoker.InvokeActionMethodAsync()\r\n   at Microsoft.AspNetCore.Mvc.Infrastructure.ControllerActionInvoker.Next(State& next, Scope& scope, Object& state, Boolean& isCompleted)\r\n   at Microsoft.AspNetCore.Mvc.Infrastructure.ControllerActionInvoker.InvokeNextActionFilterAsync()\r\n--- End of stack trace from previous location ---\r\n   at Microsoft.AspNetCore.Mvc.Infrastructure.ControllerActionInvoker.Rethrow(ActionExecutedContextSealed context)\r\n   at Microsoft.AspNetCore.Mvc.Infrastructure.ControllerActionInvoker.Next(State& next, Scope& scope, Object& state, Boolean& isCompleted)\r\n   at Microsoft.AspNetCore.Mvc.Infrastructure.ControllerActionInvoker.InvokeInnerFilterAsync()\r\n--- End of stack trace from previous location ---\r\n   at Microsoft.AspNetCore.Mvc.Infrastructure.ResourceInvoker.<InvokeNextExceptionFilterAsync>g__Awaited|26_0(ResourceInvoker invoker, Task lastTask, State next, Scope scope, Object state, Boolean isCompleted)","InstanceId":"4f3e2477","SourceContext":"Umbraco.Cms.Infrastructure.Persistence.UmbracoDatabase","ActionId":"8659d23e-ac47-42de-ba3f-fc3718348398","ActionName":"Umbraco.Forms.Web.Editors.FormController.GetOverView (Umbraco.Forms.Web)","RequestId":"80000028-0003-f300-b63f-84710c7967bb","RequestPath":"/umbraco/backoffice/UmbracoForms/Form/GetOverView","ProcessId":8944,"ProcessName":"iisexpress","ThreadId":46,"ApplicationId":"3f3ed72a8d0f46228ba494c1a1aeb400115a9d84","MachineName":"IPS-025","Log4NetLevel":"ERROR","HttpRequestId":"b35fa69f-1d1d-4045-b9fa-bbc4f5cd3f4c","HttpRequestNumber":2,"HttpSessionId":"ed0d57bf-a204-1992-3db7-99cc205f99c2"}
{"@t":"2023-11-08T09:51:45.6137954Z","@mt":"Exception ({InstanceId}).","@l":"Error","@x":"Microsoft.Data.Sqlite.SqliteException (0x80004005): SQLite Error 19: 'UNIQUE constraint failed: UFUserSecurity.User'.\r\n   at Microsoft.Data.Sqlite.SqliteException.ThrowExceptionForRC(Int32 rc, sqlite3 db)\r\n   at Microsoft.Data.Sqlite.SqliteDataReader.NextResult()\r\n   at Microsoft.Data.Sqlite.SqliteCommand.ExecuteReader(CommandBehavior behavior)\r\n   at Microsoft.Data.Sqlite.SqliteCommand.ExecuteNonQuery()\r\n   at Umbraco.Cms.Infrastructure.Persistence.FaultHandling.RetryPolicy.ExecuteAction[TResult](Func`1 func)\r\n   at NPoco.Database.ExecuteNonQueryHelper(DbCommand cmd)\r\n   at NPoco.Database.InsertAsyncImp[T](PocoData pocoData, String tableName, String primaryKeyName, Boolean autoIncrement, T poco, Boolean sync)\r\n   at NPoco.AsyncHelper.RunSync[T](Task`1 task)\r\n   at NPoco.Database.Insert[T](String tableName, String primaryKeyName, Boolean autoIncrement, T poco)\r\n   at NPoco.Database.Insert[T](T poco)\r\n   at Umbraco.Forms.Data.Storage.UserSecurityStorage.InsertUserSecurity(UserSecurity usersecurity)","InstanceId":"1a4e25b5","SourceContext":"Umbraco.Cms.Infrastructure.Persistence.UmbracoDatabase","ActionId":"4ade3f70-656d-40aa-93cf-b21911245feb","ActionName":"Umbraco.Cms.Web.BackOffice.Trees.ApplicationTreeController.GetApplicationTrees (Umbraco.Web.BackOffice)","RequestId":"8000002c-0003-f700-b63f-84710c7967bb","RequestPath":"/umbraco/backoffice/umbracotrees/applicationtree/GetApplicationTrees","ProcessId":8944,"ProcessName":"iisexpress","ThreadId":6,"ApplicationId":"3f3ed72a8d0f46228ba494c1a1aeb400115a9d84","MachineName":"IPS-025","Log4NetLevel":"ERROR","HttpRequestId":"2a27389a-3236-452d-bc3d-37ef193579be","HttpRequestNumber":3,"HttpSessionId":"c8a16e26-5c8e-29bc-9591-f3f3cccfa32d"}
{"@t":"2023-11-08T10:11:17.6328984Z","@mt":"User logged will be logged out due to timeout: {Username}, IP Address: {IPAddress}","Username":"hardikd.itpath@gmail.com","IPAddress":"::1","SourceContext":"Umbraco.Cms.Web.BackOffice.Controllers.AuthenticationController","ActionId":"4d98429e-4e9b-4fac-ab0d-2b611576ed1c","ActionName":"Umbraco.Cms.Web.BackOffice.Controllers.AuthenticationController.GetRemainingTimeoutSeconds (Umbraco.Web.BackOffice)","RequestId":"80000045-0000-f000-b63f-84710c7967bb","RequestPath":"/umbraco/backoffice/umbracoapi/authentication/GetRemainingTimeoutSeconds","ProcessId":8944,"ProcessName":"iisexpress","ThreadId":6,"ApplicationId":"3f3ed72a8d0f46228ba494c1a1aeb400115a9d84","MachineName":"IPS-025","Log4NetLevel":"INFO ","HttpRequestId":"aa1289f8-68ab-4eec-9847-7d3e307668c7","HttpRequestNumber":4,"HttpSessionId":"a0a7b319-9c75-603b-89d9-50856dd03346"}
{"@t":"2023-11-08T10:46:21.8295152Z","@mt":"Deleted {count} ContentVersion(s)","count":1,"SourceContext":"Umbraco.Cms.Infrastructure.HostedServices.ContentVersionCleanup","ProcessId":8944,"ProcessName":"iisexpress","ThreadId":92,"ApplicationId":"3f3ed72a8d0f46228ba494c1a1aeb400115a9d84","MachineName":"IPS-025","Log4NetLevel":"INFO "}
{"@t":"2023-11-08T11:33:45.6476051Z","@mt":"User logged will be logged out due to timeout: {Username}, IP Address: {IPAddress}","Username":"hardikd.itpath@gmail.com","IPAddress":"::1","SourceContext":"Umbraco.Cms.Web.BackOffice.Controllers.AuthenticationController","ActionId":"4d98429e-4e9b-4fac-ab0d-2b611576ed1c","ActionName":"Umbraco.Cms.Web.BackOffice.Controllers.AuthenticationController.GetRemainingTimeoutSeconds (Umbraco.Web.BackOffice)","RequestId":"8000000e-0003-fc00-b63f-84710c7967bb","RequestPath":"/umbraco/backoffice/umbracoapi/authentication/GetRemainingTimeoutSeconds","ProcessId":8944,"ProcessName":"iisexpress","ThreadId":45,"ApplicationId":"3f3ed72a8d0f46228ba494c1a1aeb400115a9d84","MachineName":"IPS-025","Log4NetLevel":"INFO ","HttpRequestId":"0d3fb1bc-7d79-4cd1-9f0f-8b94bd3d042c","HttpRequestNumber":5,"HttpSessionId":"6f8b13b7-552c-2177-b34f-eb67a9871bfc"}
